yass/__init__.py
yass/cli.py
yass/models.py
yass/dlx/__init__.py
yass/dlx/cover.py
yass/dlx/examples.py
yass/dlx/models.py
yass/dlx/search.py
yass/dlx/uncover.py
yass/solve/__init__.py
yass/solve/backtrack.py
yass/solve/dlx.py
yasspy-0.3.4.dist-info/LICENSE
yasspy-0.3.4.dist-info/METADATA
yasspy-0.3.4.dist-info/WHEEL
yasspy-0.3.4.dist-info/entry_points.txt
yasspy-0.3.4.dist-info/top_level.txt
yasspy-0.3.4.dist-info/RECORD
