Metadata-Version: 2.1
Name: yasspy
Version: 0.3.4
Summary: Yet another sudoku solver
Author: Sam Thorold
Author-email: sam.thorold@gmail.com
Maintainer: Sam Thorold
Maintainer-email: sam.thorold@gmail.com
License: MIT License
Project-URL: repository, https://github.com/samthorold/sudoku-python
Classifier: Programming Language :: Python :: 3
Requires-Python: >=3.10
License-File: LICENSE
Requires-Dist: typer[all]
Provides-Extra: dev
Requires-Dist: build ; extra == 'dev'
Requires-Dist: pytest-cov ; extra == 'dev'
Requires-Dist: tox ; extra == 'dev'
Requires-Dist: black ; extra == 'dev'
Requires-Dist: mypy ; extra == 'dev'
Requires-Dist: snakeviz ; extra == 'dev'
Requires-Dist: twine ; extra == 'dev'
